Metadata-Version: 2.1
Name: ansibeautifier
Version: 0.0.3
Summary: You can beautify your python command-line and GUI applications using colors
Home-page: https://www.github.com/BoughtData92730/ansibeautifier
Author: Tarun the AnyLang Programmer
Author-email: taruntheanylangprogrammer@gmail.com
License: MIT
Platform: UNKNOWN
Classifier: Development Status :: 5 - Production/Stable
Classifier: Intended Audience :: Developers
Classifier: Operating System :: Microsoft :: Windows :: Windows 10
Classifier: License :: OSI Approved :: MIT License
Classifier: Programming Language :: Python :: 3
